odoo10_addon_partner_contact_role-10.0.1.0.0-py2.7-nspkg.pth
odoo/addons/partner_contact_role/README.rst
odoo/addons/partner_contact_role/__init__.py
odoo/addons/partner_contact_role/__manifest__.py
odoo/addons/partner_contact_role/models/__init__.py
odoo/addons/partner_contact_role/models/res_partner.py
odoo/addons/partner_contact_role/security/ir.model.access.csv
odoo/addons/partner_contact_role/static/description/icon.png
odoo/addons/partner_contact_role/views/res_partner.xml
odoo/addons/partner_contact_role/views/res_partner_role.xml
odoo10_addon_partner_contact_role-10.0.1.0.0.dist-info/DESCRIPTION.rst
odoo10_addon_partner_contact_role-10.0.1.0.0.dist-info/METADATA
odoo10_addon_partner_contact_role-10.0.1.0.0.dist-info/RECORD
odoo10_addon_partner_contact_role-10.0.1.0.0.dist-info/WHEEL
odoo10_addon_partner_contact_role-10.0.1.0.0.dist-info/metadata.json
odoo10_addon_partner_contact_role-10.0.1.0.0.dist-info/namespace_packages.txt
odoo10_addon_partner_contact_role-10.0.1.0.0.dist-info/top_level.txt
