Metadata-Version: 2.0
Name: odoo10-addon-partner-contact-role
Version: 10.0.1.0.0
Summary: Add roles to partners.
Home-page: https://github.com/OCA/partner-contact
Author: Camptocamp,Odoo Community Association (OCA)
Author-email: support@odoo-community.org
License: AGPL-3
Platform: UNKNOWN
Classifier: Programming Language :: Python
Classifier: Framework :: Odoo
Classifier: License :: OSI Approved :: GNU Affero General Public License v3
Requires-Python: ~=2.7
Requires-Dist: odoo (<10.1dev,>=10.0)
